potamides/__init__.py
potamides/_version.py
potamides/_version.pyi
potamides/py.typed
potamides/splinelib.py
potamides/_src/__init__.py
potamides/_src/accelerations.py
potamides/_src/core.py
potamides/_src/custom_types.py
potamides/_src/likelihood.py
potamides/_src/plot.py
potamides/_src/splinelib/__init__.py
potamides/_src/splinelib/compat.py
potamides/_src/splinelib/data.py
potamides/_src/splinelib/funcs.py
potamides/_src/splinelib/opt.py
potamides-0.2.0.dist-info/METADATA
potamides-0.2.0.dist-info/WHEEL
potamides-0.2.0.dist-info/licenses/LICENSE
potamides-0.2.0.dist-info/RECORD
