Metadata-Version: 2.4
Name: potamides
Version: 0.2.0
Summary: Constrain gravitational potential with stream curvature
Project-URL: Homepage, https://github.com/xggs-dev/potamides
Project-URL: Bug Tracker, https://github.com/xggs-dev/potamides/issues
Project-URL: Discussions, https://github.com/xggs-dev/potamides/discussions
Project-URL: Changelog, https://github.com/xggs-dev/potamides/releases
Author-email: Jacob Nibauer <jnibauer@princeton.edu>, Nathaniel Starkman <starkman@mit.edu>, Sirui Wu <sirui.wu@nbi.ku.dk>
License-File: LICENSE
Classifier: Development Status :: 5 - Production/Stable
Classifier: Intended Audience :: Science/Research
Classifier: License :: OSI Approved :: MIT License
Classifier: Operating System :: OS Independent
Classifier: Programming Language :: Python
Classifier: Programming Language :: Python :: 3
Classifier: Programming Language :: Python :: 3 :: Only
Classifier: Programming Language :: Python :: 3.11
Classifier: Programming Language :: Python :: 3.12
Classifier: Programming Language :: Python :: 3.13
Classifier: Topic :: Scientific/Engineering
Classifier: Typing :: Typed
Requires-Python: >=3.11
Requires-Dist: astropy>=7.0
Requires-Dist: galax
Requires-Dist: interpax>=0.3.8
Requires-Dist: jax>=0.5.3
Requires-Dist: jaxtyping>=0.3.1
Requires-Dist: matplotlib>=3.10.1
Requires-Dist: numpy>=2.2.3
Requires-Dist: optax>=0.2.4
Requires-Dist: scipy>=1.15.2
Requires-Dist: typing-extensions>=4.13.2
Requires-Dist: unxt>=1.6.2
Requires-Dist: xmmutablemap>=0.1
